{
  "$schema": "https://schema.management.azure.com/schemas/2015-01-01/deploymentParameters.json#",
  "contentVersion": "1.0.0.0",
  "parameters": {
    "planName": {
      "value": "plan-PRODUCT-ENVIRONMENT-001"
    },
    "name": {
      "value": "func-PRODUCT-ENVIRONMENT-001"
    },
    "workspaceName": {
      "value": "work-PRODUCT-ENVIRONMENT-001"
    },
    "storageName": {
      "value": "stPRODUCTENVIRONMENT001"
    },
    "appInsightsKey": {
      "value": "APPI-KEY"
    },
    "appInsightsConnection": {
      "value": "APPI-CONNECTION-STRING"
    },
    "sku": {
      "value": "Dynamic"
    },
    "sku": {
      "value": "Y1"
    },
    "workerSize": {
      "value": "0"
    },
    "workerSizeId": {
      "value": "0"
    },
    "numberOfWorkers": {
      "value": "1"
    },
    "use32BitWorkerProcess": {
      "value": true
    }
  }
}